pygbn/__init__.py
pygbn/gbn.py
pygbn-0.1.3.dist-info/METADATA
pygbn-0.1.3.dist-info/WHEEL
pygbn-0.1.3.dist-info/top_level.txt
pygbn-0.1.3.dist-info/RECORD
