Metadata-Version: 2.4
Name: pygbn
Version: 0.1.3
Summary: Python implementation of Generalized Binary Noise
Author-email: Maximilian Stölzle <maximilian@stoelzle.ch>
License: MIT
Project-URL: Homepage, https://github.com/tud-phi/pygbn
Project-URL: Bug Reports, https://github.com/tud-phi/pygbn/issues
Project-URL: Source, https://github.com/tud-phi/pygbn/
Keywords: binary noise,signal generation,system identification,test signals
Classifier: Development Status :: 3 - Alpha
Classifier: Intended Audience :: Developers
Classifier: Topic :: Scientific/Engineering
Classifier: Programming Language :: Python :: 3
Classifier: Programming Language :: Python :: 3.8
Classifier: Programming Language :: Python :: 3.9
Classifier: Programming Language :: Python :: 3.10
Classifier: Programming Language :: Python :: 3.11
Classifier: Programming Language :: Python :: 3.12
Classifier: Programming Language :: Python :: 3.13
Classifier: Programming Language :: Python :: 3.14
Classifier: Programming Language :: Python :: 3 :: Only
Requires-Python: >=3.8
Requires-Dist: peppercorn
Requires-Dist: numpy
Provides-Extra: dev
Requires-Dist: check-manifest; extra == "dev"
Requires-Dist: matplotlib; extra == "dev"
Provides-Extra: test
Requires-Dist: coverage; extra == "test"
Requires-Dist: pytest; extra == "test"
